{
  "date": "2026-06-18",
  "primes": {
    "360ONE": {
      "ticker": "360ONE",
      "status": "SIGNAL",
      "current_price": 1136.9,
      "target_3pct": 1171.01,
      "target_nearing": false,
      "ema9": 1104.99,
      "ema9_value": 1104.99,
      "sma50_value": 1078.13,
      "above_sma50": true,
      "ema9_dist_pct": 2.89,
      "breakout_date": "2026-06-12",
      "breakout_close": 1096.8,
      "breakout_high": 1099.0,
      "confirm_date": "2026-06-15",
      "confirm_close": 1130.8,
      "candles_ago": 2,
      "interval": "1d",
      "candles": [
        {
          "date": "2026-03-20",
          "open": 1028.63,
          "high": 1048.91,
          "low": 1028.63,
          "close": 1034.59,
          "volume": 413078,
          "ema9": 1042.48,
          "sma50": 1104.99,
          "is_breakout": false,
          "is_confirm": false
        },
        {
          "date": "2026-03-23",
          "open": 1034.59,
          "high": 1034.59,
          "low": 968.28,
          "close": 979.71,
          "volume": 550431,
          "ema9": 1029.93,
          "sma50": 1100.88,
          "is_breakout": false,
          "is_confirm": false
        },
        {
          "date": "2026-03-24",
          "open": 990.25,
          "high": 1004.17,
          "low": 978.62,
          "close": 983.59,
          "volume": 2023338,
          "ema9": 1020.66,
          "sma50": 1097.03,
          "is_breakout": false,
          "is_confirm": false
        },
        {
          "date": "2026-03-25",
          "open": 994.03,
          "high": 1012.92,
          "low": 986.37,
          "close": 996.32,
          "volume": 871077,
          "ema9": 1015.79,
          "sma50": 1094.27,
          "is_breakout": false,
          "is_confirm": false
        },
        {
          "date": "2026-03-27",
          "open": 992.24,
          "high": 993.13,
          "low": 964.2,
          "close": 971.76,
          "volume": 602539,
          "ema9": 1006.98,
          "sma50": 1091.23,
          "is_breakout": false,
          "is_confirm": false
        },
        {
          "date": "2026-03-30",
          "open": 963.51,
          "high": 963.51,
          "low": 926.72,
          "close": 944.12,
          "volume": 1347427,
          "ema9": 994.41,
          "sma50": 1087.51,
          "is_breakout": false,
          "is_confirm": false
        },
        {
          "date": "2026-04-01",
          "open": 960.47,
          "high": 977.03,
          "low": 944.52,
          "close": 947.55,
          "volume": 610228,
          "ema9": 985.04,
          "sma50": 1083.61,
          "is_breakout": false,
          "is_confirm": false
        },
        {
          "date": "2026-04-02",
          "open": 930.6,
          "high": 934.82,
          "low": 909.72,
          "close": 928.46,
          "volume": 636396,
          "ema9": 973.72,
          "sma50": 1078.36,
          "is_breakout": false,
          "is_confirm": false
        },
        {
          "date": "2026-04-06",
          "open": 925.63,
          "high": 934.82,
          "low": 913.25,
          "close": 924.09,
          "volume": 2743646,
          "ema9": 963.8,
          "sma50": 1073.57,
          "is_breakout": false,
          "is_confirm": false
        },
        {
          "date": "2026-04-07",
          "open": 919.81,
          "high": 929.31,
          "low": 900.82,
          "close": 923.89,
          "volume": 703930,
          "ema9": 955.81,
          "sma50": 1069.59,
          "is_breakout": false,
          "is_confirm": false
        },
        {
          "date": "2026-04-08",
          "open": 956.45,
          "high": 980.16,
          "low": 953.02,
          "close": 966.09,
          "volume": 3000755,
          "ema9": 957.87,
          "sma50": 1067.13,
          "is_breakout": false,
          "is_confirm": false
        },
        {
          "date": "2026-04-09",
          "open": 966.14,
          "high": 1010.09,
          "low": 959.03,
          "close": 992.34,
          "volume": 3056871,
          "ema9": 964.76,
          "sma50": 1064.98,
          "is_breakout": false,
          "is_confirm": false
        },
        {
          "date": "2026-04-10",
          "open": 992.24,
          "high": 1016.1,
          "low": 986.92,
          "close": 1006.81,
          "volume": 1139241,
          "ema9": 973.17,
          "sma50": 1063.0,
          "is_breakout": false,
          "is_confirm": false
        },
        {
          "date": "2026-04-13",
          "open": 985.28,
          "high": 1009.79,
          "low": 970.76,
          "close": 1003.67,
          "volume": 604509,
          "ema9": 979.27,
          "sma50": 1060.93,
          "is_breakout": false,
          "is_confirm": false
        },
        {
          "date": "2026-04-15",
          "open": 1021.02,
          "high": 1059.65,
          "low": 1014.36,
          "close": 1049.91,
          "volume": 1795093,
          "ema9": 993.4,
          "sma50": 1059.26,
          "is_breakout": false,
          "is_confirm": false
        },
        {
          "date": "2026-04-16",
          "open": 1064.82,
          "high": 1078.74,
          "low": 1050.8,
          "close": 1070.24,
          "volume": 796315,
          "ema9": 1008.77,
          "sma50": 1058.08,
          "is_breakout": false,
          "is_confirm": false
        },
        {
          "date": "2026-04-17",
          "open": 1077.74,
          "high": 1117.51,
          "low": 1072.62,
          "close": 1106.87,
          "volume": 2641982,
          "ema9": 1028.39,
          "sma50": 1057.66,
          "is_breakout": false,
          "is_confirm": false
        },
        {
          "date": "2026-04-20",
          "open": 1101.31,
          "high": 1121.14,
          "low": 1090.42,
          "close": 1102.85,
          "volume": 671866,
          "ema9": 1043.28,
          "sma50": 1057.64,
          "is_breakout": false,
          "is_confirm": false
        },
        {
          "date": "2026-04-21",
          "open": 1109.56,
          "high": 1125.47,
          "low": 1090.17,
          "close": 1101.95,
          "volume": 1199787,
          "ema9": 1055.01,
          "sma50": 1056.46,
          "is_breakout": false,
          "is_confirm": false
        },
        {
          "date": "2026-04-22",
          "open": 1107.57,
          "high": 1117.31,
          "low": 1035.99,
          "close": 1048.81,
          "volume": 5903548,
          "ema9": 1053.77,
          "sma50": 1054.25,
          "is_breakout": false,
          "is_confirm": false
        },
        {
          "date": "2026-04-23",
          "open": 1042.95,
          "high": 1050.9,
          "low": 1027.83,
          "close": 1046.18,
          "volume": 1335631,
          "ema9": 1052.25,
          "sma50": 1052.49,
          "is_breakout": false,
          "is_confirm": false
        },
        {
          "date": "2026-04-24",
          "open": 1050.8,
          "high": 1056.32,
          "low": 1024.25,
          "close": 1033.6,
          "volume": 896365,
          "ema9": 1048.52,
          "sma50": 1051.01,
          "is_breakout": false,
          "is_confirm": false
        },
        {
          "date": "2026-04-27",
          "open": 1034.9,
          "high": 1046.45,
          "low": 1025.0,
          "close": 1042.05,
          "volume": 592351,
          "ema9": 1047.23,
          "sma50": 1049.22,
          "is_breakout": false,
          "is_confirm": false
        },
        {
          "date": "2026-04-28",
          "open": 1041.0,
          "high": 1049.5,
          "low": 1030.05,
          "close": 1038.95,
          "volume": 645825,
          "ema9": 1045.57,
          "sma50": 1046.88,
          "is_breakout": false,
          "is_confirm": false
        },
        {
          "date": "2026-04-29",
          "open": 1045.0,
          "high": 1055.5,
          "low": 1034.15,
          "close": 1046.8,
          "volume": 687054,
          "ema9": 1045.82,
          "sma50": 1045.18,
          "is_breakout": false,
          "is_confirm": false
        },
        {
          "date": "2026-04-30",
          "open": 1038.2,
          "high": 1041.35,
          "low": 1009.0,
          "close": 1034.65,
          "volume": 1026753,
          "ema9": 1043.58,
          "sma50": 1043.12,
          "is_breakout": false,
          "is_confirm": false
        },
        {
          "date": "2026-05-01",
          "open": 1034.65,
          "high": 1034.65,
          "low": 1034.65,
          "close": 1034.65,
          "volume": 0,
          "ema9": 1041.8,
          "sma50": 1041.41,
          "is_breakout": false,
          "is_confirm": false
        },
        {
          "date": "2026-05-04",
          "open": 1041.0,
          "high": 1072.4,
          "low": 1033.4,
          "close": 1066.5,
          "volume": 2455293,
          "ema9": 1046.74,
          "sma50": 1040.47,
          "is_breakout": false,
          "is_confirm": false
        },
        {
          "date": "2026-05-05",
          "open": 1065.6,
          "high": 1085.6,
          "low": 1050.5,
          "close": 1070.7,
          "volume": 1750453,
          "ema9": 1051.53,
          "sma50": 1039.52,
          "is_breakout": false,
          "is_confirm": false
        },
        {
          "date": "2026-05-06",
          "open": 1079.8,
          "high": 1097.6,
          "low": 1075.0,
          "close": 1084.1,
          "volume": 2173450,
          "ema9": 1058.04,
          "sma50": 1038.79,
          "is_breakout": false,
          "is_confirm": false
        },
        {
          "date": "2026-05-07",
          "open": 1084.1,
          "high": 1118.0,
          "low": 1083.0,
          "close": 1111.7,
          "volume": 809803,
          "ema9": 1068.78,
          "sma50": 1039.06,
          "is_breakout": false,
          "is_confirm": false
        },
        {
          "date": "2026-05-08",
          "open": 1112.9,
          "high": 1134.9,
          "low": 1105.7,
          "close": 1118.5,
          "volume": 732727,
          "ema9": 1078.72,
          "sma50": 1039.55,
          "is_breakout": false,
          "is_confirm": false
        },
        {
          "date": "2026-05-11",
          "open": 1115.0,
          "high": 1134.4,
          "low": 1111.0,
          "close": 1115.3,
          "volume": 935561,
          "ema9": 1086.04,
          "sma50": 1039.45,
          "is_breakout": false,
          "is_confirm": false
        },
        {
          "date": "2026-05-12",
          "open": 1105.1,
          "high": 1115.3,
          "low": 1075.0,
          "close": 1078.1,
          "volume": 925297,
          "ema9": 1084.45,
          "sma50": 1038.87,
          "is_breakout": false,
          "is_confirm": false
        },
        {
          "date": "2026-05-13",
          "open": 1070.0,
          "high": 1100.0,
          "low": 1070.0,
          "close": 1077.5,
          "volume": 568085,
          "ema9": 1083.06,
          "sma50": 1037.91,
          "is_breakout": false,
          "is_confirm": false
        },
        {
          "date": "2026-05-14",
          "open": 1080.1,
          "high": 1106.7,
          "low": 1062.0,
          "close": 1102.1,
          "volume": 403296,
          "ema9": 1086.87,
          "sma50": 1037.52,
          "is_breakout": false,
          "is_confirm": false
        },
        {
          "date": "2026-05-15",
          "open": 1116.1,
          "high": 1123.5,
          "low": 1090.0,
          "close": 1093.8,
          "volume": 684883,
          "ema9": 1088.25,
          "sma50": 1037.45,
          "is_breakout": false,
          "is_confirm": false
        },
        {
          "date": "2026-05-18",
          "open": 1085.0,
          "high": 1111.8,
          "low": 1066.8,
          "close": 1104.9,
          "volume": 661233,
          "ema9": 1091.58,
          "sma50": 1038.18,
          "is_breakout": false,
          "is_confirm": false
        },
        {
          "date": "2026-05-19",
          "open": 1104.0,
          "high": 1121.5,
          "low": 1092.0,
          "close": 1098.4,
          "volume": 442746,
          "ema9": 1092.95,
          "sma50": 1038.94,
          "is_breakout": false,
          "is_confirm": false
        },
        {
          "date": "2026-05-20",
          "open": 1090.1,
          "high": 1111.0,
          "low": 1076.0,
          "close": 1107.4,
          "volume": 310456,
          "ema9": 1095.84,
          "sma50": 1039.6,
          "is_breakout": false,
          "is_confirm": false
        },
        {
          "date": "2026-05-21",
          "open": 1118.8,
          "high": 1131.0,
          "low": 1105.2,
          "close": 1111.8,
          "volume": 833753,
          "ema9": 1099.03,
          "sma50": 1040.67,
          "is_breakout": false,
          "is_confirm": false
        },
        {
          "date": "2026-05-22",
          "open": 1110.6,
          "high": 1121.8,
          "low": 1103.0,
          "close": 1112.4,
          "volume": 482891,
          "ema9": 1101.7,
          "sma50": 1042.34,
          "is_breakout": false,
          "is_confirm": false
        },
        {
          "date": "2026-05-25",
          "open": 1125.4,
          "high": 1144.4,
          "low": 1119.1,
          "close": 1142.4,
          "volume": 725309,
          "ema9": 1109.84,
          "sma50": 1044.19,
          "is_breakout": false,
          "is_confirm": false
        },
        {
          "date": "2026-05-26",
          "open": 1152.0,
          "high": 1152.0,
          "low": 1121.7,
          "close": 1125.3,
          "volume": 762091,
          "ema9": 1112.93,
          "sma50": 1045.85,
          "is_breakout": false,
          "is_confirm": false
        },
        {
          "date": "2026-05-27",
          "open": 1125.9,
          "high": 1129.5,
          "low": 1109.2,
          "close": 1112.1,
          "volume": 274760,
          "ema9": 1112.77,
          "sma50": 1047.35,
          "is_breakout": false,
          "is_confirm": false
        },
        {
          "date": "2026-05-28",
          "open": 1112.1,
          "high": 1112.1,
          "low": 1112.1,
          "close": 1112.1,
          "volume": 0,
          "ema9": 1112.63,
          "sma50": 1049.16,
          "is_breakout": false,
          "is_confirm": false
        },
        {
          "date": "2026-05-29",
          "open": 1118.0,
          "high": 1127.8,
          "low": 1095.0,
          "close": 1104.5,
          "volume": 1006275,
          "ema9": 1111.01,
          "sma50": 1050.91,
          "is_breakout": false,
          "is_confirm": false
        },
        {
          "date": "2026-06-01",
          "open": 1108.0,
          "high": 1114.9,
          "low": 1069.8,
          "close": 1078.8,
          "volume": 1197416,
          "ema9": 1104.57,
          "sma50": 1051.74,
          "is_breakout": false,
          "is_confirm": false
        },
        {
          "date": "2026-06-02",
          "open": 1070.0,
          "high": 1093.0,
          "low": 1051.8,
          "close": 1089.2,
          "volume": 1196484,
          "ema9": 1101.49,
          "sma50": 1052.25,
          "is_breakout": false,
          "is_confirm": false
        },
        {
          "date": "2026-06-03",
          "open": 1082.5,
          "high": 1085.6,
          "low": 1049.2,
          "close": 1072.5,
          "volume": 765530,
          "ema9": 1095.69,
          "sma50": 1053.01,
          "is_breakout": false,
          "is_confirm": false
        },
        {
          "date": "2026-06-04",
          "open": 1064.3,
          "high": 1081.5,
          "low": 1062.1,
          "close": 1071.8,
          "volume": 2527568,
          "ema9": 1090.92,
          "sma50": 1053.76,
          "is_breakout": false,
          "is_confirm": false
        },
        {
          "date": "2026-06-05",
          "open": 1068.0,
          "high": 1093.3,
          "low": 1050.7,
          "close": 1073.9,
          "volume": 2432019,
          "ema9": 1087.51,
          "sma50": 1055.64,
          "is_breakout": false,
          "is_confirm": false
        },
        {
          "date": "2026-06-08",
          "open": 1068.0,
          "high": 1068.9,
          "low": 1047.7,
          "close": 1054.9,
          "volume": 344987,
          "ema9": 1080.99,
          "sma50": 1057.07,
          "is_breakout": false,
          "is_confirm": false
        },
        {
          "date": "2026-06-09",
          "open": 1056.4,
          "high": 1083.0,
          "low": 1056.4,
          "close": 1075.0,
          "volume": 384782,
          "ema9": 1079.79,
          "sma50": 1058.64,
          "is_breakout": false,
          "is_confirm": false
        },
        {
          "date": "2026-06-10",
          "open": 1080.0,
          "high": 1080.0,
          "low": 1048.0,
          "close": 1052.0,
          "volume": 947964,
          "ema9": 1074.23,
          "sma50": 1060.24,
          "is_breakout": false,
          "is_confirm": false
        },
        {
          "date": "2026-06-11",
          "open": 1041.7,
          "high": 1071.7,
          "low": 1031.3,
          "close": 1064.1,
          "volume": 690962,
          "ema9": 1072.21,
          "sma50": 1062.64,
          "is_breakout": false,
          "is_confirm": false
        },
        {
          "date": "2026-06-12",
          "open": 1079.7,
          "high": 1099.0,
          "low": 1058.0,
          "close": 1096.8,
          "volume": 696601,
          "ema9": 1077.13,
          "sma50": 1065.63,
          "is_breakout": true,
          "is_confirm": false
        },
        {
          "date": "2026-06-15",
          "open": 1109.8,
          "high": 1134.7,
          "low": 1106.0,
          "close": 1130.8,
          "volume": 2132710,
          "ema9": 1087.86,
          "sma50": 1069.68,
          "is_breakout": false,
          "is_confirm": true
        },
        {
          "date": "2026-06-16",
          "open": 1143.2,
          "high": 1165.1,
          "low": 1130.3,
          "close": 1133.6,
          "volume": 1168609,
          "ema9": 1097.01,
          "sma50": 1073.87,
          "is_breakout": false,
          "is_confirm": false
        },
        {
          "date": "2026-06-17",
          "open": 1160.0,
          "high": 1160.0,
          "low": 1127.0,
          "close": 1136.9,
          "volume": 382759,
          "ema9": 1104.99,
          "sma50": 1078.13,
          "is_breakout": false,
          "is_confirm": false
        }
      ],
      "trend_regime": "SIDEWAYS",
      "sma50": 1078.13,
      "sma200": 1089.53,
      "lr_slope_pct": 0.2304,
      "above_50sma": true,
      "above_200sma": true,
      "composite_fair_price": 1158.63,
      "valuation_bucket": "FAIR",
      "fv_error": null,
      "fv_model_count": 1,
      "fair_gap_pct": 1.91,
      "gap_to_fair_pct": 1.91,
      "composite_gain_pct": 1.91
    },
    "RECLTD": {
      "ticker": "RECLTD",
      "status": "SIGNAL",
      "current_price": 358.75,
      "target_3pct": 369.51,
      "target_nearing": false,
      "ema9": 349.12,
      "ema9_value": 349.12,
      "sma50_value": 351.06,
      "above_sma50": true,
      "ema9_dist_pct": 2.76,
      "breakout_date": "2026-06-12",
      "breakout_close": 348.05,
      "breakout_high": 348.75,
      "confirm_date": "2026-06-15",
      "confirm_close": 351.85,
      "candles_ago": 2,
      "interval": "1d",
      "candles": [
        {
          "date": "2026-03-20",
          "open": 335.8,
          "high": 342.0,
          "low": 329.25,
          "close": 330.5,
          "volume": 10305459,
          "ema9": 333.82,
          "sma50": 350.12,
          "is_breakout": false,
          "is_confirm": false
        },
        {
          "date": "2026-03-23",
          "open": 327.45,
          "high": 327.45,
          "low": 310.55,
          "close": 316.45,
          "volume": 11748371,
          "ema9": 330.34,
          "sma50": 349.18,
          "is_breakout": false,
          "is_confirm": false
        },
        {
          "date": "2026-03-24",
          "open": 322.5,
          "high": 325.8,
          "low": 312.05,
          "close": 320.8,
          "volume": 8845151,
          "ema9": 328.43,
          "sma50": 348.48,
          "is_breakout": false,
          "is_confirm": false
        },
        {
          "date": "2026-03-25",
          "open": 324.9,
          "high": 329.15,
          "low": 323.25,
          "close": 327.7,
          "volume": 6889607,
          "ema9": 328.29,
          "sma50": 347.79,
          "is_breakout": false,
          "is_confirm": false
        },
        {
          "date": "2026-03-27",
          "open": 326.0,
          "high": 326.0,
          "low": 317.55,
          "close": 318.45,
          "volume": 8875060,
          "ema9": 326.32,
          "sma50": 346.98,
          "is_breakout": false,
          "is_confirm": false
        },
        {
          "date": "2026-03-30",
          "open": 314.25,
          "high": 317.7,
          "low": 304.05,
          "close": 305.1,
          "volume": 16723499,
          "ema9": 322.08,
          "sma50": 345.84,
          "is_breakout": false,
          "is_confirm": false
        },
        {
          "date": "2026-04-01",
          "open": 319.8,
          "high": 323.7,
          "low": 312.35,
          "close": 322.1,
          "volume": 9592156,
          "ema9": 322.08,
          "sma50": 345.04,
          "is_breakout": false,
          "is_confirm": false
        },
        {
          "date": "2026-04-02",
          "open": 317.55,
          "high": 325.95,
          "low": 311.25,
          "close": 324.8,
          "volume": 8100516,
          "ema9": 322.62,
          "sma50": 344.28,
          "is_breakout": false,
          "is_confirm": false
        },
        {
          "date": "2026-04-06",
          "open": 323.55,
          "high": 328.25,
          "low": 320.2,
          "close": 327.55,
          "volume": 6505082,
          "ema9": 323.61,
          "sma50": 343.59,
          "is_breakout": false,
          "is_confirm": false
        },
        {
          "date": "2026-04-07",
          "open": 325.9,
          "high": 330.6,
          "low": 325.0,
          "close": 329.35,
          "volume": 8232651,
          "ema9": 324.76,
          "sma50": 343.15,
          "is_breakout": false,
          "is_confirm": false
        },
        {
          "date": "2026-04-08",
          "open": 344.85,
          "high": 344.85,
          "low": 337.6,
          "close": 342.65,
          "volume": 6840941,
          "ema9": 328.34,
          "sma50": 343.04,
          "is_breakout": false,
          "is_confirm": false
        },
        {
          "date": "2026-04-09",
          "open": 342.65,
          "high": 349.85,
          "low": 338.7,
          "close": 346.8,
          "volume": 6287331,
          "ema9": 332.03,
          "sma50": 342.81,
          "is_breakout": false,
          "is_confirm": false
        },
        {
          "date": "2026-04-10",
          "open": 349.0,
          "high": 354.3,
          "low": 345.9,
          "close": 349.8,
          "volume": 6438338,
          "ema9": 335.58,
          "sma50": 342.73,
          "is_breakout": false,
          "is_confirm": false
        },
        {
          "date": "2026-04-13",
          "open": 341.15,
          "high": 347.85,
          "low": 337.75,
          "close": 347.0,
          "volume": 5524253,
          "ema9": 337.87,
          "sma50": 342.55,
          "is_breakout": false,
          "is_confirm": false
        },
        {
          "date": "2026-04-15",
          "open": 350.6,
          "high": 356.25,
          "low": 350.15,
          "close": 352.65,
          "volume": 5663934,
          "ema9": 340.82,
          "sma50": 342.22,
          "is_breakout": false,
          "is_confirm": false
        },
        {
          "date": "2026-04-16",
          "open": 355.0,
          "high": 372.6,
          "low": 354.0,
          "close": 364.2,
          "volume": 21771221,
          "ema9": 345.5,
          "sma50": 342.16,
          "is_breakout": false,
          "is_confirm": false
        },
        {
          "date": "2026-04-17",
          "open": 364.15,
          "high": 377.7,
          "low": 362.7,
          "close": 373.3,
          "volume": 14949943,
          "ema9": 351.06,
          "sma50": 342.5,
          "is_breakout": false,
          "is_confirm": false
        },
        {
          "date": "2026-04-20",
          "open": 373.35,
          "high": 384.55,
          "low": 366.45,
          "close": 382.7,
          "volume": 12043689,
          "ema9": 357.39,
          "sma50": 343.05,
          "is_breakout": false,
          "is_confirm": false
        },
        {
          "date": "2026-04-21",
          "open": 382.7,
          "high": 387.45,
          "low": 380.0,
          "close": 383.35,
          "volume": 8374408,
          "ema9": 362.58,
          "sma50": 343.42,
          "is_breakout": false,
          "is_confirm": false
        },
        {
          "date": "2026-04-22",
          "open": 380.0,
          "high": 386.25,
          "low": 379.0,
          "close": 383.35,
          "volume": 5284649,
          "ema9": 366.73,
          "sma50": 343.62,
          "is_breakout": false,
          "is_confirm": false
        },
        {
          "date": "2026-04-23",
          "open": 381.85,
          "high": 386.1,
          "low": 375.85,
          "close": 376.45,
          "volume": 6915475,
          "ema9": 368.68,
          "sma50": 343.67,
          "is_breakout": false,
          "is_confirm": false
        },
        {
          "date": "2026-04-24",
          "open": 377.0,
          "high": 378.75,
          "low": 369.05,
          "close": 374.0,
          "volume": 4834153,
          "ema9": 369.74,
          "sma50": 343.78,
          "is_breakout": false,
          "is_confirm": false
        },
        {
          "date": "2026-04-27",
          "open": 376.0,
          "high": 381.95,
          "low": 376.0,
          "close": 378.05,
          "volume": 4948268,
          "ema9": 371.4,
          "sma50": 344.21,
          "is_breakout": false,
          "is_confirm": false
        },
        {
          "date": "2026-04-28",
          "open": 377.0,
          "high": 383.5,
          "low": 371.5,
          "close": 375.8,
          "volume": 10991705,
          "ema9": 372.28,
          "sma50": 344.68,
          "is_breakout": false,
          "is_confirm": false
        },
        {
          "date": "2026-04-29",
          "open": 368.05,
          "high": 372.45,
          "low": 358.1,
          "close": 363.55,
          "volume": 16891422,
          "ema9": 370.54,
          "sma50": 344.94,
          "is_breakout": false,
          "is_confirm": false
        },
        {
          "date": "2026-04-30",
          "open": 361.1,
          "high": 361.1,
          "low": 352.75,
          "close": 354.3,
          "volume": 9031675,
          "ema9": 367.29,
          "sma50": 345.07,
          "is_breakout": false,
          "is_confirm": false
        },
        {
          "date": "2026-05-01",
          "open": 354.3,
          "high": 354.3,
          "low": 354.3,
          "close": 354.3,
          "volume": 0,
          "ema9": 364.69,
          "sma50": 345.29,
          "is_breakout": false,
          "is_confirm": false
        },
        {
          "date": "2026-05-04",
          "open": 356.0,
          "high": 361.15,
          "low": 351.4,
          "close": 353.5,
          "volume": 5034010,
          "ema9": 362.45,
          "sma50": 345.36,
          "is_breakout": false,
          "is_confirm": false
        },
        {
          "date": "2026-05-05",
          "open": 353.5,
          "high": 357.8,
          "low": 351.15,
          "close": 356.4,
          "volume": 6734583,
          "ema9": 361.24,
          "sma50": 345.38,
          "is_breakout": false,
          "is_confirm": false
        },
        {
          "date": "2026-05-06",
          "open": 358.9,
          "high": 361.1,
          "low": 351.85,
          "close": 359.1,
          "volume": 9798302,
          "ema9": 360.81,
          "sma50": 345.35,
          "is_breakout": false,
          "is_confirm": false
        },
        {
          "date": "2026-05-07",
          "open": 360.0,
          "high": 367.3,
          "low": 357.6,
          "close": 359.75,
          "volume": 7776265,
          "ema9": 360.6,
          "sma50": 345.54,
          "is_breakout": false,
          "is_confirm": false
        },
        {
          "date": "2026-05-08",
          "open": 359.75,
          "high": 363.6,
          "low": 356.15,
          "close": 359.4,
          "volume": 5059153,
          "ema9": 360.36,
          "sma50": 345.71,
          "is_breakout": false,
          "is_confirm": false
        },
        {
          "date": "2026-05-11",
          "open": 358.0,
          "high": 358.8,
          "low": 350.5,
          "close": 351.55,
          "volume": 4773107,
          "ema9": 358.6,
          "sma50": 345.77,
          "is_breakout": false,
          "is_confirm": false
        },
        {
          "date": "2026-05-12",
          "open": 350.15,
          "high": 353.65,
          "low": 343.55,
          "close": 344.35,
          "volume": 5222169,
          "ema9": 355.75,
          "sma50": 345.64,
          "is_breakout": false,
          "is_confirm": false
        },
        {
          "date": "2026-05-13",
          "open": 345.45,
          "high": 351.1,
          "low": 342.0,
          "close": 346.55,
          "volume": 4765260,
          "ema9": 353.91,
          "sma50": 345.56,
          "is_breakout": false,
          "is_confirm": false
        },
        {
          "date": "2026-05-14",
          "open": 349.0,
          "high": 350.55,
          "low": 341.7,
          "close": 348.3,
          "volume": 5287354,
          "ema9": 352.79,
          "sma50": 345.51,
          "is_breakout": false,
          "is_confirm": false
        },
        {
          "date": "2026-05-15",
          "open": 349.5,
          "high": 350.25,
          "low": 344.2,
          "close": 345.85,
          "volume": 3222539,
          "ema9": 351.4,
          "sma50": 345.5,
          "is_breakout": false,
          "is_confirm": false
        },
        {
          "date": "2026-05-18",
          "open": 345.0,
          "high": 345.0,
          "low": 331.65,
          "close": 333.7,
          "volume": 6159707,
          "ema9": 347.86,
          "sma50": 345.46,
          "is_breakout": false,
          "is_confirm": false
        },
        {
          "date": "2026-05-19",
          "open": 333.7,
          "high": 337.15,
          "low": 332.8,
          "close": 334.25,
          "volume": 2521354,
          "ema9": 345.14,
          "sma50": 345.63,
          "is_breakout": false,
          "is_confirm": false
        },
        {
          "date": "2026-05-20",
          "open": 333.4,
          "high": 335.0,
          "low": 328.15,
          "close": 333.0,
          "volume": 3723835,
          "ema9": 342.71,
          "sma50": 345.52,
          "is_breakout": false,
          "is_confirm": false
        },
        {
          "date": "2026-05-21",
          "open": 336.4,
          "high": 338.8,
          "low": 333.0,
          "close": 333.7,
          "volume": 4807537,
          "ema9": 340.91,
          "sma50": 345.48,
          "is_breakout": false,
          "is_confirm": false
        },
        {
          "date": "2026-05-22",
          "open": 335.5,
          "high": 338.0,
          "low": 332.4,
          "close": 336.95,
          "volume": 4613260,
          "ema9": 340.12,
          "sma50": 345.79,
          "is_breakout": false,
          "is_confirm": false
        },
        {
          "date": "2026-05-25",
          "open": 340.0,
          "high": 345.0,
          "low": 340.0,
          "close": 342.2,
          "volume": 3489013,
          "ema9": 340.53,
          "sma50": 346.01,
          "is_breakout": false,
          "is_confirm": false
        },
        {
          "date": "2026-05-26",
          "open": 344.0,
          "high": 344.45,
          "low": 336.3,
          "close": 337.6,
          "volume": 3913330,
          "ema9": 339.95,
          "sma50": 346.17,
          "is_breakout": false,
          "is_confirm": false
        },
        {
          "date": "2026-05-27",
          "open": 337.0,
          "high": 340.65,
          "low": 336.6,
          "close": 339.7,
          "volume": 3232759,
          "ema9": 339.9,
          "sma50": 346.16,
          "is_breakout": false,
          "is_confirm": false
        },
        {
          "date": "2026-05-28",
          "open": 339.7,
          "high": 339.7,
          "low": 339.7,
          "close": 339.7,
          "volume": 0,
          "ema9": 339.86,
          "sma50": 346.38,
          "is_breakout": false,
          "is_confirm": false
        },
        {
          "date": "2026-05-29",
          "open": 342.5,
          "high": 343.65,
          "low": 335.0,
          "close": 337.65,
          "volume": 10274190,
          "ema9": 339.42,
          "sma50": 346.55,
          "is_breakout": false,
          "is_confirm": false
        },
        {
          "date": "2026-06-01",
          "open": 339.65,
          "high": 339.85,
          "low": 331.0,
          "close": 331.4,
          "volume": 4076940,
          "ema9": 337.81,
          "sma50": 346.49,
          "is_breakout": false,
          "is_confirm": false
        },
        {
          "date": "2026-06-02",
          "open": 329.95,
          "high": 330.4,
          "low": 321.0,
          "close": 325.05,
          "volume": 6501043,
          "ema9": 335.26,
          "sma50": 346.1,
          "is_breakout": false,
          "is_confirm": false
        },
        {
          "date": "2026-06-03",
          "open": 325.8,
          "high": 327.5,
          "low": 322.6,
          "close": 325.65,
          "volume": 4526029,
          "ema9": 333.34,
          "sma50": 346.01,
          "is_breakout": false,
          "is_confirm": false
        },
        {
          "date": "2026-06-04",
          "open": 325.65,
          "high": 336.2,
          "low": 325.1,
          "close": 335.2,
          "volume": 8844070,
          "ema9": 333.71,
          "sma50": 346.1,
          "is_breakout": false,
          "is_confirm": false
        },
        {
          "date": "2026-06-05",
          "open": 336.8,
          "high": 346.8,
          "low": 336.2,
          "close": 343.9,
          "volume": 11008792,
          "ema9": 335.75,
          "sma50": 346.65,
          "is_breakout": false,
          "is_confirm": false
        },
        {
          "date": "2026-06-08",
          "open": 340.0,
          "high": 346.4,
          "low": 338.45,
          "close": 343.4,
          "volume": 11062037,
          "ema9": 337.28,
          "sma50": 347.1,
          "is_breakout": false,
          "is_confirm": false
        },
        {
          "date": "2026-06-09",
          "open": 344.25,
          "high": 352.8,
          "low": 343.45,
          "close": 352.1,
          "volume": 6850589,
          "ema9": 340.24,
          "sma50": 347.59,
          "is_breakout": false,
          "is_confirm": false
        },
        {
          "date": "2026-06-10",
          "open": 352.0,
          "high": 354.8,
          "low": 347.8,
          "close": 348.8,
          "volume": 4341800,
          "ema9": 341.95,
          "sma50": 348.2,
          "is_breakout": false,
          "is_confirm": false
        },
        {
          "date": "2026-06-11",
          "open": 348.5,
          "high": 349.55,
          "low": 335.7,
          "close": 336.85,
          "volume": 5830091,
          "ema9": 340.93,
          "sma50": 348.83,
          "is_breakout": false,
          "is_confirm": false
        },
        {
          "date": "2026-06-12",
          "open": 341.25,
          "high": 348.75,
          "low": 339.9,
          "close": 348.05,
          "volume": 2634728,
          "ema9": 342.36,
          "sma50": 349.35,
          "is_breakout": true,
          "is_confirm": false
        },
        {
          "date": "2026-06-15",
          "open": 353.7,
          "high": 354.45,
          "low": 350.5,
          "close": 351.85,
          "volume": 3911854,
          "ema9": 344.26,
          "sma50": 349.89,
          "is_breakout": false,
          "is_confirm": true
        },
        {
          "date": "2026-06-16",
          "open": 353.0,
          "high": 358.75,
          "low": 352.4,
          "close": 356.55,
          "volume": 3407173,
          "ema9": 346.71,
          "sma50": 350.47,
          "is_breakout": false,
          "is_confirm": false
        },
        {
          "date": "2026-06-17",
          "open": 357.5,
          "high": 360.0,
          "low": 354.3,
          "close": 358.75,
          "volume": 2690056,
          "ema9": 349.12,
          "sma50": 351.06,
          "is_breakout": false,
          "is_confirm": false
        }
      ],
      "trend_regime": "SIDEWAYS",
      "sma50": 351.06,
      "sma200": 351.45,
      "lr_slope_pct": 0.0203,
      "above_50sma": true,
      "above_200sma": true,
      "composite_fair_price": 396.75,
      "valuation_bucket": "FAIR",
      "fv_error": null,
      "fv_model_count": 3,
      "fair_gap_pct": 10.59,
      "gap_to_fair_pct": 10.59,
      "composite_gain_pct": 10.59
    },
    "ICICIBANK": {
      "ticker": "ICICIBANK",
      "status": "SIGNAL",
      "current_price": 1336.8,
      "target_3pct": 1376.9,
      "target_nearing": true,
      "ema9": 1310.27,
      "ema9_value": 1310.27,
      "sma50_value": 1287.77,
      "above_sma50": true,
      "ema9_dist_pct": 2.02,
      "breakout_date": "2026-06-09",
      "breakout_close": 1275.0,
      "breakout_high": 1279.9,
      "confirm_date": "2026-06-10",
      "confirm_close": 1293.3,
      "candles_ago": 5,
      "interval": "1d",
      "candles": [
        {
          "date": "2026-03-20",
          "open": 1258.4,
          "high": 1274.0,
          "low": 1241.7,
          "close": 1245.4,
          "volume": 16421006,
          "ema9": 1278.41,
          "sma50": 1366.96,
          "is_breakout": false,
          "is_confirm": false
        },
        {
          "date": "2026-03-23",
          "open": 1226.6,
          "high": 1234.9,
          "low": 1218.1,
          "close": 1222.7,
          "volume": 17049534,
          "ema9": 1267.27,
          "sma50": 1362.72,
          "is_breakout": false,
          "is_confirm": false
        },
        {
          "date": "2026-03-24",
          "open": 1237.1,
          "high": 1253.9,
          "low": 1223.7,
          "close": 1251.2,
          "volume": 20617782,
          "ema9": 1264.06,
          "sma50": 1359.65,
          "is_breakout": false,
          "is_confirm": false
        },
        {
          "date": "2026-03-25",
          "open": 1258.9,
          "high": 1272.9,
          "low": 1254.4,
          "close": 1259.7,
          "volume": 17290030,
          "ema9": 1263.18,
          "sma50": 1356.59,
          "is_breakout": false,
          "is_confirm": false
        },
        {
          "date": "2026-03-27",
          "open": 1256.0,
          "high": 1260.9,
          "low": 1230.1,
          "close": 1233.8,
          "volume": 23630905,
          "ema9": 1257.31,
          "sma50": 1352.52,
          "is_breakout": false,
          "is_confirm": false
        },
        {
          "date": "2026-03-30",
          "open": 1216.5,
          "high": 1222.6,
          "low": 1200.4,
          "close": 1205.9,
          "volume": 23952775,
          "ema9": 1247.03,
          "sma50": 1348.27,
          "is_breakout": false,
          "is_confirm": false
        },
        {
          "date": "2026-04-01",
          "open": 1228.1,
          "high": 1234.0,
          "low": 1210.0,
          "close": 1212.7,
          "volume": 25472333,
          "ema9": 1240.16,
          "sma50": 1344.16,
          "is_breakout": false,
          "is_confirm": false
        },
        {
          "date": "2026-04-02",
          "open": 1196.0,
          "high": 1222.1,
          "low": 1187.6,
          "close": 1215.8,
          "volume": 20851722,
          "ema9": 1235.29,
          "sma50": 1340.26,
          "is_breakout": false,
          "is_confirm": false
        },
        {
          "date": "2026-04-06",
          "open": 1213.0,
          "high": 1234.4,
          "low": 1200.5,
          "close": 1231.4,
          "volume": 10058414,
          "ema9": 1234.51,
          "sma50": 1337.27,
          "is_breakout": false,
          "is_confirm": false
        },
        {
          "date": "2026-04-07",
          "open": 1229.0,
          "high": 1250.4,
          "low": 1216.6,
          "close": 1245.5,
          "volume": 25600557,
          "ema9": 1236.71,
          "sma50": 1334.67,
          "is_breakout": false,
          "is_confirm": false
        },
        {
          "date": "2026-04-08",
          "open": 1310.0,
          "high": 1333.5,
          "low": 1292.4,
          "close": 1309.2,
          "volume": 25148651,
          "ema9": 1251.21,
          "sma50": 1333.87,
          "is_breakout": false,
          "is_confirm": false
        },
        {
          "date": "2026-04-09",
          "open": 1299.9,
          "high": 1308.0,
          "low": 1275.9,
          "close": 1281.3,
          "volume": 22923062,
          "ema9": 1257.23,
          "sma50": 1332.59,
          "is_breakout": false,
          "is_confirm": false
        },
        {
          "date": "2026-04-10",
          "open": 1289.0,
          "high": 1324.0,
          "low": 1288.5,
          "close": 1321.9,
          "volume": 18174755,
          "ema9": 1270.16,
          "sma50": 1332.16,
          "is_breakout": false,
          "is_confirm": false
        },
        {
          "date": "2026-04-13",
          "open": 1304.9,
          "high": 1357.0,
          "low": 1296.7,
          "close": 1351.1,
          "volume": 30572141,
          "ema9": 1286.35,
          "sma50": 1331.95,
          "is_breakout": false,
          "is_confirm": false
        },
        {
          "date": "2026-04-15",
          "open": 1358.0,
          "high": 1364.8,
          "low": 1338.0,
          "close": 1348.1,
          "volume": 23827473,
          "ema9": 1298.7,
          "sma50": 1331.56,
          "is_breakout": false,
          "is_confirm": false
        },
        {
          "date": "2026-04-16",
          "open": 1352.0,
          "high": 1366.9,
          "low": 1340.2,
          "close": 1345.5,
          "volume": 24017236,
          "ema9": 1308.06,
          "sma50": 1330.8,
          "is_breakout": false,
          "is_confirm": false
        },
        {
          "date": "2026-04-17",
          "open": 1347.0,
          "high": 1352.9,
          "low": 1334.0,
          "close": 1346.8,
          "volume": 18151993,
          "ema9": 1315.81,
          "sma50": 1330.63,
          "is_breakout": false,
          "is_confirm": false
        },
        {
          "date": "2026-04-20",
          "open": 1364.7,
          "high": 1376.4,
          "low": 1353.0,
          "close": 1356.2,
          "volume": 21551520,
          "ema9": 1323.89,
          "sma50": 1330.7,
          "is_breakout": false,
          "is_confirm": false
        },
        {
          "date": "2026-04-21",
          "open": 1368.0,
          "high": 1393.1,
          "low": 1360.0,
          "close": 1388.4,
          "volume": 23312455,
          "ema9": 1336.79,
          "sma50": 1330.68,
          "is_breakout": false,
          "is_confirm": false
        },
        {
          "date": "2026-04-22",
          "open": 1380.0,
          "high": 1380.1,
          "low": 1365.0,
          "close": 1367.6,
          "volume": 13613487,
          "ema9": 1342.95,
          "sma50": 1329.86,
          "is_breakout": false,
          "is_confirm": false
        },
        {
          "date": "2026-04-23",
          "open": 1348.4,
          "high": 1354.0,
          "low": 1343.5,
          "close": 1348.0,
          "volume": 20111792,
          "ema9": 1343.96,
          "sma50": 1328.89,
          "is_breakout": false,
          "is_confirm": false
        },
        {
          "date": "2026-04-24",
          "open": 1336.3,
          "high": 1348.8,
          "low": 1324.0,
          "close": 1326.2,
          "volume": 14056743,
          "ema9": 1340.41,
          "sma50": 1327.29,
          "is_breakout": false,
          "is_confirm": false
        },
        {
          "date": "2026-04-27",
          "open": 1327.9,
          "high": 1335.9,
          "low": 1310.9,
          "close": 1314.1,
          "volume": 15385625,
          "ema9": 1335.15,
          "sma50": 1325.65,
          "is_breakout": false,
          "is_confirm": false
        },
        {
          "date": "2026-04-28",
          "open": 1314.3,
          "high": 1317.7,
          "low": 1286.7,
          "close": 1292.0,
          "volume": 16774778,
          "ema9": 1326.52,
          "sma50": 1323.36,
          "is_breakout": false,
          "is_confirm": false
        },
        {
          "date": "2026-04-29",
          "open": 1294.7,
          "high": 1296.8,
          "low": 1276.2,
          "close": 1281.0,
          "volume": 11716030,
          "ema9": 1317.41,
          "sma50": 1320.86,
          "is_breakout": false,
          "is_confirm": false
        },
        {
          "date": "2026-04-30",
          "open": 1261.0,
          "high": 1272.2,
          "low": 1259.0,
          "close": 1263.4,
          "volume": 17740110,
          "ema9": 1306.61,
          "sma50": 1317.52,
          "is_breakout": false,
          "is_confirm": false
        },
        {
          "date": "2026-05-01",
          "open": 1263.4,
          "high": 1263.4,
          "low": 1263.4,
          "close": 1263.4,
          "volume": 0,
          "ema9": 1297.97,
          "sma50": 1314.5,
          "is_breakout": false,
          "is_confirm": false
        },
        {
          "date": "2026-05-04",
          "open": 1264.3,
          "high": 1282.2,
          "low": 1264.3,
          "close": 1270.8,
          "volume": 14597051,
          "ema9": 1292.54,
          "sma50": 1311.68,
          "is_breakout": false,
          "is_confirm": false
        },
        {
          "date": "2026-05-05",
          "open": 1264.0,
          "high": 1266.7,
          "low": 1245.5,
          "close": 1251.3,
          "volume": 24447935,
          "ema9": 1284.29,
          "sma50": 1308.56,
          "is_breakout": false,
          "is_confirm": false
        },
        {
          "date": "2026-05-06",
          "open": 1262.0,
          "high": 1282.8,
          "low": 1252.1,
          "close": 1279.5,
          "volume": 22909586,
          "ema9": 1283.33,
          "sma50": 1305.99,
          "is_breakout": false,
          "is_confirm": false
        },
        {
          "date": "2026-05-07",
          "open": 1284.7,
          "high": 1294.0,
          "low": 1273.2,
          "close": 1279.0,
          "volume": 25028552,
          "ema9": 1282.46,
          "sma50": 1303.79,
          "is_breakout": false,
          "is_confirm": false
        },
        {
          "date": "2026-05-08",
          "open": 1279.6,
          "high": 1279.6,
          "low": 1261.2,
          "close": 1264.8,
          "volume": 11137424,
          "ema9": 1278.93,
          "sma50": 1301.2,
          "is_breakout": false,
          "is_confirm": false
        },
        {
          "date": "2026-05-11",
          "open": 1259.4,
          "high": 1275.7,
          "low": 1252.0,
          "close": 1266.4,
          "volume": 18980488,
          "ema9": 1276.43,
          "sma50": 1298.54,
          "is_breakout": false,
          "is_confirm": false
        },
        {
          "date": "2026-05-12",
          "open": 1256.0,
          "high": 1259.9,
          "low": 1236.3,
          "close": 1240.3,
          "volume": 21110708,
          "ema9": 1269.2,
          "sma50": 1295.65,
          "is_breakout": false,
          "is_confirm": false
        },
        {
          "date": "2026-05-13",
          "open": 1238.3,
          "high": 1249.2,
          "low": 1227.2,
          "close": 1235.6,
          "volume": 19490295,
          "ema9": 1262.48,
          "sma50": 1292.35,
          "is_breakout": false,
          "is_confirm": false
        },
        {
          "date": "2026-05-14",
          "open": 1239.1,
          "high": 1256.7,
          "low": 1236.0,
          "close": 1246.0,
          "volume": 16535600,
          "ema9": 1259.18,
          "sma50": 1289.17,
          "is_breakout": false,
          "is_confirm": false
        },
        {
          "date": "2026-05-15",
          "open": 1246.6,
          "high": 1258.0,
          "low": 1242.0,
          "close": 1244.5,
          "volume": 11745614,
          "ema9": 1256.25,
          "sma50": 1286.48,
          "is_breakout": false,
          "is_confirm": false
        },
        {
          "date": "2026-05-18",
          "open": 1235.5,
          "high": 1253.7,
          "low": 1232.0,
          "close": 1251.1,
          "volume": 13918850,
          "ema9": 1255.22,
          "sma50": 1284.02,
          "is_breakout": false,
          "is_confirm": false
        },
        {
          "date": "2026-05-19",
          "open": 1251.1,
          "high": 1256.3,
          "low": 1229.8,
          "close": 1240.8,
          "volume": 38929053,
          "ema9": 1252.33,
          "sma50": 1281.53,
          "is_breakout": false,
          "is_confirm": false
        },
        {
          "date": "2026-05-20",
          "open": 1230.0,
          "high": 1239.7,
          "low": 1223.3,
          "close": 1237.3,
          "volume": 14953103,
          "ema9": 1249.33,
          "sma50": 1279.13,
          "is_breakout": false,
          "is_confirm": false
        },
        {
          "date": "2026-05-21",
          "open": 1245.3,
          "high": 1248.3,
          "low": 1234.4,
          "close": 1242.8,
          "volume": 14394386,
          "ema9": 1248.02,
          "sma50": 1277.71,
          "is_breakout": false,
          "is_confirm": false
        },
        {
          "date": "2026-05-22",
          "open": 1242.0,
          "high": 1270.8,
          "low": 1242.0,
          "close": 1264.3,
          "volume": 11601085,
          "ema9": 1251.28,
          "sma50": 1277.43,
          "is_breakout": false,
          "is_confirm": false
        },
        {
          "date": "2026-05-25",
          "open": 1271.0,
          "high": 1293.5,
          "low": 1270.9,
          "close": 1291.8,
          "volume": 13853923,
          "ema9": 1259.38,
          "sma50": 1277.03,
          "is_breakout": false,
          "is_confirm": false
        },
        {
          "date": "2026-05-26",
          "open": 1290.0,
          "high": 1301.8,
          "low": 1276.2,
          "close": 1279.1,
          "volume": 18400405,
          "ema9": 1263.33,
          "sma50": 1276.72,
          "is_breakout": false,
          "is_confirm": false
        },
        {
          "date": "2026-05-27",
          "open": 1286.0,
          "high": 1293.4,
          "low": 1266.7,
          "close": 1272.7,
          "volume": 18366272,
          "ema9": 1265.2,
          "sma50": 1276.84,
          "is_breakout": false,
          "is_confirm": false
        },
        {
          "date": "2026-05-28",
          "open": 1272.7,
          "high": 1272.7,
          "low": 1272.7,
          "close": 1272.7,
          "volume": 0,
          "ema9": 1266.7,
          "sma50": 1277.2,
          "is_breakout": false,
          "is_confirm": false
        },
        {
          "date": "2026-05-29",
          "open": 1275.1,
          "high": 1287.8,
          "low": 1247.9,
          "close": 1256.4,
          "volume": 31007884,
          "ema9": 1264.64,
          "sma50": 1276.87,
          "is_breakout": false,
          "is_confirm": false
        },
        {
          "date": "2026-06-01",
          "open": 1257.1,
          "high": 1261.9,
          "low": 1235.9,
          "close": 1239.7,
          "volume": 9911975,
          "ema9": 1259.65,
          "sma50": 1275.89,
          "is_breakout": false,
          "is_confirm": false
        },
        {
          "date": "2026-06-02",
          "open": 1233.0,
          "high": 1237.7,
          "low": 1220.7,
          "close": 1226.6,
          "volume": 17920892,
          "ema9": 1253.04,
          "sma50": 1274.64,
          "is_breakout": false,
          "is_confirm": false
        },
        {
          "date": "2026-06-03",
          "open": 1219.9,
          "high": 1248.3,
          "low": 1213.7,
          "close": 1242.0,
          "volume": 13934754,
          "ema9": 1250.83,
          "sma50": 1274.48,
          "is_breakout": false,
          "is_confirm": false
        },
        {
          "date": "2026-06-04",
          "open": 1232.2,
          "high": 1262.3,
          "low": 1232.2,
          "close": 1251.7,
          "volume": 19461560,
          "ema9": 1251.01,
          "sma50": 1274.6,
          "is_breakout": false,
          "is_confirm": false
        },
        {
          "date": "2026-06-05",
          "open": 1257.0,
          "high": 1265.0,
          "low": 1250.0,
          "close": 1262.1,
          "volume": 10166393,
          "ema9": 1253.23,
          "sma50": 1275.39,
          "is_breakout": false,
          "is_confirm": false
        },
        {
          "date": "2026-06-08",
          "open": 1246.4,
          "high": 1254.0,
          "low": 1243.1,
          "close": 1250.2,
          "volume": 10714196,
          "ema9": 1252.62,
          "sma50": 1275.37,
          "is_breakout": false,
          "is_confirm": false
        },
        {
          "date": "2026-06-09",
          "open": 1255.0,
          "high": 1279.9,
          "low": 1252.7,
          "close": 1275.0,
          "volume": 22368579,
          "ema9": 1257.1,
          "sma50": 1275.68,
          "is_breakout": true,
          "is_confirm": false
        },
        {
          "date": "2026-06-10",
          "open": 1271.3,
          "high": 1306.0,
          "low": 1271.3,
          "close": 1293.3,
          "volume": 25951584,
          "ema9": 1264.34,
          "sma50": 1276.87,
          "is_breakout": false,
          "is_confirm": true
        },
        {
          "date": "2026-06-11",
          "open": 1286.5,
          "high": 1333.0,
          "low": 1286.5,
          "close": 1317.0,
          "volume": 35919374,
          "ema9": 1274.87,
          "sma50": 1279.09,
          "is_breakout": false,
          "is_confirm": false
        },
        {
          "date": "2026-06-12",
          "open": 1330.0,
          "high": 1344.3,
          "low": 1318.7,
          "close": 1340.8,
          "volume": 18339846,
          "ema9": 1288.06,
          "sma50": 1281.65,
          "is_breakout": false,
          "is_confirm": false
        },
        {
          "date": "2026-06-15",
          "open": 1354.6,
          "high": 1362.7,
          "low": 1325.3,
          "close": 1327.6,
          "volume": 16172921,
          "ema9": 1295.96,
          "sma50": 1283.89,
          "is_breakout": false,
          "is_confirm": false
        },
        {
          "date": "2026-06-16",
          "open": 1331.9,
          "high": 1337.3,
          "low": 1326.3,
          "close": 1334.3,
          "volume": 13069159,
          "ema9": 1303.63,
          "sma50": 1285.94,
          "is_breakout": false,
          "is_confirm": false
        },
        {
          "date": "2026-06-17",
          "open": 1342.0,
          "high": 1346.0,
          "low": 1333.4,
          "close": 1336.8,
          "volume": 8026424,
          "ema9": 1310.27,
          "sma50": 1287.77,
          "is_breakout": false,
          "is_confirm": false
        }
      ],
      "trend_regime": "SIDEWAYS",
      "sma50": 1287.77,
      "sma200": 1345.98,
      "lr_slope_pct": 0.0107,
      "above_50sma": true,
      "above_200sma": false,
      "composite_fair_price": 1406.2,
      "valuation_bucket": "FAIR",
      "fv_error": null,
      "fv_model_count": 3,
      "fair_gap_pct": 5.19,
      "gap_to_fair_pct": 5.19,
      "composite_gain_pct": 5.19
    }
  }
}